spark_celery/__init__.py
spark_celery/app.py
spark_celery/cache.py
spark_celery/loader.py
spark_celery/main.py
spark_celery/task.py
spark_celery-0.2.dist-info/LICENSE
spark_celery-0.2.dist-info/METADATA
spark_celery-0.2.dist-info/WHEEL
spark_celery-0.2.dist-info/top_level.txt
spark_celery-0.2.dist-info/RECORD
