Metadata-Version: 2.1
Name: spark-celery
Version: 0.2
Summary: A helper to allow Python Celery tasks to do work in a Spark job
Home-page: https://github.com/gregbaker/spark-celery
Download-URL: https://codeload.github.com/gregbaker/spark-celery/zip/master
Author: Greg Baker
Author-email: ggbaker@sfu.ca
Keywords: spark,celery,bigdata
Classifier: Development Status :: 4 - Beta
Classifier: License :: OSI Approved :: Apache Software License
Classifier: Programming Language :: Python :: 2
Classifier: Programming Language :: Python :: 3
Classifier: Operating System :: OS Independent
Classifier: Topic :: System :: Distributed Computing
License-File: LICENSE
Requires-Dist: celery
Requires-Dist: kombu
